robot/Logo.py
robot/SDK.py
robot/__init__.py
robot/__main__.py
robot/config.toml
elite_ec_sdk-0.0.2.dist-info/LICENSE
elite_ec_sdk-0.0.2.dist-info/METADATA
elite_ec_sdk-0.0.2.dist-info/WHEEL
elite_ec_sdk-0.0.2.dist-info/entry_points.txt
elite_ec_sdk-0.0.2.dist-info/top_level.txt
elite_ec_sdk-0.0.2.dist-info/RECORD
