Metadata-Version: 2.1
Name: elite-ec-sdk
Version: 0.0.2
Summary: SDK for Elite EC Series Cobots
Author-email: Tushar Gaurav <tushar.gaurav416@gmail.com>
License: MIT License
Project-URL: Homepage, https://github.com/tushgaurav/EliteECSeriesSDK
Keywords: elite-sdk,elite-ec,elite-robots
Classifier: License :: OSI Approved :: MIT License
Classifier: Programming Language :: Python
Classifier: Programming Language :: Python :: 3
Requires-Python: >=3.1
License-File: LICENSE
Requires-Dist: tomli ; python_version < "3.11"
Provides-Extra: dev
Requires-Dist: black ; extra == 'dev'
Requires-Dist: bumpver ; extra == 'dev'
Requires-Dist: isort ; extra == 'dev'
Requires-Dist: pip-tools ; extra == 'dev'
